guerilla_parser/__init__.py
guerilla_parser/exception.py
guerilla_parser/node.py
guerilla_parser/parser.py
guerilla_parser/plug.py
guerilla_parser/util.py
guerilla_parser-0.8.5.dist-info/licenses/LICENSE
guerilla_parser-0.8.5.dist-info/METADATA
guerilla_parser-0.8.5.dist-info/WHEEL
guerilla_parser-0.8.5.dist-info/top_level.txt
guerilla_parser-0.8.5.dist-info/RECORD
